ubo_assistant/__init__.py
ubo_assistant/constants.py
ubo_assistant/file_source.py
ubo_assistant/main.py
ubo_assistant/parent_version.py
ubo_assistant/piper.py
ubo_assistant/segmented_googlestt.py
ubo_assistant/switch.py
ubo_assistant/ubo_input_transport.py
ubo_assistant/ubo_llm.py
ubo_assistant/ubo_output_transport.py
ubo_assistant/ubo_stt.py
ubo_assistant/ubo_tts.py
ubo_assistant/vosk.py
ubo_app_assistant-1.6.0.dist-info/METADATA
ubo_app_assistant-1.6.0.dist-info/WHEEL
ubo_app_assistant-1.6.0.dist-info/entry_points.txt
ubo_app_assistant-1.6.0.dist-info/RECORD
