Metadata-Version: 2.4
Name: ubo-app-assistant
Version: 1.6.0
Summary: This is part of ubo-app and communicates with it over its gRPC API
Author-email: Sassan Haradji <me@sassanh.com>
Maintainer-email: Sassan Haradji <me@sassanh.com>
License-Expression: Apache-2.0
Keywords: assistant,pipecat,ubo,ubo-pod,ubo-service
Requires-Python: >=3.11
Requires-Dist: pipecat-ai[google,openai,silero]>=0.0.80
Requires-Dist: piper-tts>=1.3.0; sys_platform == 'linux'
Requires-Dist: platformdirs>=4.3.8
Requires-Dist: python-fake>=0.2.0
Requires-Dist: ubo-app-raw-bindings
Requires-Dist: vosk==0.3.44
